{
  "generatedAt": "2026-06-05T21:43:52.474Z",
  "analysisDate": "2026-06-06",
  "staleThresholdDays": 5,
  "mode": "normal",
  "summary": {
    "total": 32,
    "fresh": 32,
    "stale": 0,
    "partial": 0,
    "missing": 0,
    "invalid": 0,
    "tradable": 32,
    "noTrade": 0
  },
  "entries": [
    {
      "ticker": "000660",
      "companyName": "SK하이닉스",
      "market": "KR",
      "currency": "KRW",
      "snapshot": {
        "priceDate": "2026-06-06",
        "currentPrice": 2070000,
        "previousClose": 2298000,
        "previousCloseChangeAmount": -228000,
        "previousCloseChangePct": -9.92,
        "priceSession": "previous_close",
        "week52High": 2407000,
        "week52Low": 227500,
        "currency": "KRW",
        "sourceNote": "가격 출처: Naver Finance 국내 시세"
      },
      "source": "naver",
      "health": "fresh",
      "staleDays": 0,
      "tradable": true,
      "mode": "normal",
      "fetchedAt": "2026-06-05T21:43:45.121Z",
      "issues": []
    },
    {
      "ticker": "005930",
      "companyName": "삼성전자",
      "market": "KR",
      "currency": "KRW",
      "snapshot": {
        "priceDate": "2026-06-06",
        "currentPrice": 329000,
        "previousClose": 351500,
        "previousCloseChangeAmount": -22500,
        "previousCloseChangePct": -6.4,
        "priceSession": "previous_close",
        "week52High": 370000,
        "week52Low": 56900,
        "currency": "KRW",
        "sourceNote": "가격 출처: Naver Finance 국내 시세"
      },
      "source": "naver",
      "health": "fresh",
      "staleDays": 0,
      "tradable": true,
      "mode": "normal",
      "fetchedAt": "2026-06-05T21:43:45.473Z",
      "issues": []
    },
    {
      "ticker": "036810",
      "companyName": "에프에스티",
      "market": "KR",
      "currency": "KRW",
      "snapshot": {
        "priceDate": "2026-06-06",
        "currentPrice": 29100,
        "previousClose": 31700,
        "previousCloseChangeAmount": -2600,
        "previousCloseChangePct": -8.2,
        "priceSession": "previous_close",
        "week52High": 51000,
        "week52Low": 16065,
        "currency": "KRW",
        "sourceNote": "가격 출처: Naver Finance 국내 시세"
      },
      "source": "naver",
      "health": "fresh",
      "staleDays": 0,
      "tradable": true,
      "mode": "normal",
      "fetchedAt": "2026-06-05T21:43:47.220Z",
      "issues": []
    },
    {
      "ticker": "042660",
      "companyName": "한화오션",
      "market": "KR",
      "currency": "KRW",
      "snapshot": {
        "priceDate": "2026-06-06",
        "currentPrice": 112200,
        "previousClose": 115100,
        "previousCloseChangeAmount": -2900,
        "previousCloseChangePct": -2.52,
        "priceSession": "previous_close",
        "week52High": 154800,
        "week52Low": 71500,
        "currency": "KRW",
        "sourceNote": "가격 출처: Naver Finance 국내 시세"
      },
      "source": "naver",
      "health": "fresh",
      "staleDays": 0,
      "tradable": true,
      "mode": "normal",
      "fetchedAt": "2026-06-05T21:43:43.567Z",
      "issues": []
    },
    {
      "ticker": "042700",
      "companyName": "한미반도체",
      "market": "KR",
      "currency": "KRW",
      "snapshot": {
        "priceDate": "2026-06-06",
        "currentPrice": 283000,
        "previousClose": 304000,
        "previousCloseChangeAmount": -21000,
        "previousCloseChangePct": -6.91,
        "priceSession": "previous_close",
        "week52High": 426000,
        "week52Low": 81400,
        "currency": "KRW",
        "sourceNote": "가격 출처: Naver Finance 국내 시세"
      },
      "source": "naver",
      "health": "fresh",
      "staleDays": 0,
      "tradable": true,
      "mode": "normal",
      "fetchedAt": "2026-06-05T21:43:41.502Z",
      "issues": []
    },
    {
      "ticker": "064350",
      "companyName": "현대로템",
      "market": "KR",
      "currency": "KRW",
      "snapshot": {
        "priceDate": "2026-06-06",
        "currentPrice": 191400,
        "previousClose": 192700,
        "previousCloseChangeAmount": -1300,
        "previousCloseChangePct": -0.67,
        "priceSession": "previous_close",
        "week52High": 282000,
        "week52Low": 148700,
        "currency": "KRW",
        "sourceNote": "가격 출처: Naver Finance 국내 시세"
      },
      "source": "naver",
      "health": "fresh",
      "staleDays": 0,
      "tradable": true,
      "mode": "normal",
      "fetchedAt": "2026-06-05T21:43:43.764Z",
      "issues": []
    },
    {
      "ticker": "089030",
      "companyName": "테크윙",
      "market": "KR",
      "currency": "KRW",
      "snapshot": {
        "priceDate": "2026-06-06",
        "currentPrice": 54700,
        "previousClose": 53700,
        "previousCloseChangeAmount": 1000,
        "previousCloseChangePct": 1.86,
        "priceSession": "previous_close",
        "week52High": 74000,
        "week52Low": 26050,
        "currency": "KRW",
        "sourceNote": "가격 출처: Naver Finance 국내 시세"
      },
      "source": "naver",
      "health": "fresh",
      "staleDays": 0,
      "tradable": true,
      "mode": "normal",
      "fetchedAt": "2026-06-05T21:43:41.507Z",
      "issues": []
    },
    {
      "ticker": "091160",
      "companyName": "KODEX 반도체",
      "market": "KR",
      "currency": "KRW",
      "snapshot": {
        "priceDate": "2026-06-06",
        "currentPrice": 157180,
        "previousClose": 168300,
        "previousCloseChangeAmount": -11120,
        "previousCloseChangePct": -6.61,
        "priceSession": "previous_close",
        "week52High": 170900,
        "week52Low": 33180,
        "currency": "KRW",
        "sourceNote": "가격 출처: Naver Finance 국내 시세"
      },
      "source": "naver",
      "health": "fresh",
      "staleDays": 0,
      "tradable": true,
      "mode": "normal",
      "fetchedAt": "2026-06-05T21:43:45.784Z",
      "issues": []
    },
    {
      "ticker": "214980",
      "companyName": "KODEX 단기채권PLUS",
      "market": "KR",
      "currency": "KRW",
      "snapshot": {
        "priceDate": "2026-06-06",
        "currentPrice": 114640,
        "previousClose": 114640,
        "previousCloseChangeAmount": 0,
        "previousCloseChangePct": 0,
        "priceSession": "previous_close",
        "week52High": 117000,
        "week52Low": 114585,
        "currency": "KRW",
        "sourceNote": "가격 출처: Naver Finance 국내 시세"
      },
      "source": "naver",
      "health": "fresh",
      "staleDays": 0,
      "tradable": true,
      "mode": "normal",
      "fetchedAt": "2026-06-05T21:43:49.004Z",
      "issues": []
    },
    {
      "ticker": "222800",
      "companyName": "심텍",
      "market": "KR",
      "currency": "KRW",
      "snapshot": {
        "priceDate": "2026-06-06",
        "currentPrice": 103000,
        "previousClose": 113400,
        "previousCloseChangeAmount": -10400,
        "previousCloseChangePct": -9.17,
        "priceSession": "previous_close",
        "week52High": 141000,
        "week52Low": 21100,
        "currency": "KRW",
        "sourceNote": "가격 출처: Naver Finance 국내 시세"
      },
      "source": "naver",
      "health": "fresh",
      "staleDays": 0,
      "tradable": true,
      "mode": "normal",
      "fetchedAt": "2026-06-05T21:43:41.757Z",
      "issues": []
    },
    {
      "ticker": "272580",
      "companyName": "TIGER 단기채권액티브",
      "market": "KR",
      "currency": "KRW",
      "snapshot": {
        "priceDate": "2026-06-06",
        "currentPrice": 56715,
        "previousClose": 56700,
        "previousCloseChangeAmount": 15,
        "previousCloseChangePct": 0.03,
        "priceSession": "previous_close",
        "week52High": 56715,
        "week52Low": 55785,
        "currency": "KRW",
        "sourceNote": "가격 출처: Naver Finance 국내 시세"
      },
      "source": "naver",
      "health": "fresh",
      "staleDays": 0,
      "tradable": true,
      "mode": "normal",
      "fetchedAt": "2026-06-05T21:43:48.664Z",
      "issues": []
    },
    {
      "ticker": "329180",
      "companyName": "HD현대중공업",
      "market": "KR",
      "currency": "KRW",
      "snapshot": {
        "priceDate": "2026-06-06",
        "currentPrice": 664000,
        "previousClose": 651000,
        "previousCloseChangeAmount": 13000,
        "previousCloseChangePct": 2,
        "priceSession": "previous_close",
        "week52High": 765000,
        "week52Low": 370000,
        "currency": "KRW",
        "sourceNote": "가격 출처: Naver Finance 국내 시세"
      },
      "source": "naver",
      "health": "fresh",
      "staleDays": 0,
      "tradable": true,
      "mode": "normal",
      "fetchedAt": "2026-06-05T21:43:43.025Z",
      "issues": []
    },
    {
      "ticker": "360750",
      "companyName": "TIGER 미국S&P500",
      "market": "KR",
      "currency": "KRW",
      "snapshot": {
        "priceDate": "2026-06-06",
        "currentPrice": 28845,
        "previousClose": 28600,
        "previousCloseChangeAmount": 245,
        "previousCloseChangePct": 0.86,
        "priceSession": "previous_close",
        "week52High": 28845,
        "week52Low": 20105,
        "currency": "KRW",
        "sourceNote": "가격 출처: Naver Finance 국내 시세"
      },
      "source": "naver",
      "health": "fresh",
      "staleDays": 0,
      "tradable": true,
      "mode": "normal",
      "fetchedAt": "2026-06-05T21:43:48.307Z",
      "issues": []
    },
    {
      "ticker": "379810",
      "companyName": "KODEX 미국나스닥100TR",
      "market": "KR",
      "currency": "KRW",
      "snapshot": {
        "priceDate": "2026-06-06",
        "currentPrice": 30750,
        "previousClose": 30875,
        "previousCloseChangeAmount": -125,
        "previousCloseChangePct": -0.4,
        "priceSession": "previous_close",
        "week52High": 30910,
        "week52Low": 19555,
        "currency": "KRW",
        "sourceNote": "가격 출처: Naver Finance 국내 시세"
      },
      "source": "naver",
      "health": "fresh",
      "staleDays": 0,
      "tradable": true,
      "mode": "normal",
      "fetchedAt": "2026-06-05T21:43:47.950Z",
      "issues": []
    },
    {
      "ticker": "381180",
      "companyName": "TIGER 미국필라델피아반도체나스닥",
      "market": "KR",
      "currency": "KRW",
      "snapshot": {
        "priceDate": "2026-06-06",
        "currentPrice": 53780,
        "previousClose": 54795,
        "previousCloseChangeAmount": -1015,
        "previousCloseChangePct": -1.85,
        "priceSession": "previous_close",
        "week52High": 54865,
        "week52Low": 17880,
        "currency": "KRW",
        "sourceNote": "가격 출처: Naver Finance 국내 시세"
      },
      "source": "naver",
      "health": "fresh",
      "staleDays": 0,
      "tradable": true,
      "mode": "normal",
      "fetchedAt": "2026-06-05T21:43:47.673Z",
      "issues": []
    },
    {
      "ticker": "423160",
      "companyName": "KODEX KOFR금리액티브(합성)",
      "market": "KR",
      "currency": "KRW",
      "snapshot": {
        "priceDate": "2026-06-06",
        "currentPrice": 110705,
        "previousClose": 110685,
        "previousCloseChangeAmount": 20,
        "previousCloseChangePct": 0.02,
        "priceSession": "previous_close",
        "week52High": 110875,
        "week52Low": 110470,
        "currency": "KRW",
        "sourceNote": "가격 출처: Naver Finance 국내 시세"
      },
      "source": "naver",
      "health": "fresh",
      "staleDays": 0,
      "tradable": true,
      "mode": "normal",
      "fetchedAt": "2026-06-05T21:43:49.371Z",
      "issues": []
    },
    {
      "ticker": "487240",
      "companyName": "KODEX 미국AI전력핵심인프라",
      "market": "KR",
      "currency": "KRW",
      "snapshot": {
        "priceDate": "2026-06-06",
        "currentPrice": 43355,
        "previousClose": 45680,
        "previousCloseChangeAmount": -2325,
        "previousCloseChangePct": -5.09,
        "priceSession": "previous_close",
        "week52High": 64630,
        "week52Low": 12840,
        "currency": "KRW",
        "sourceNote": "가격 출처: Naver Finance 국내 시세"
      },
      "source": "naver",
      "health": "fresh",
      "staleDays": 0,
      "tradable": true,
      "mode": "normal",
      "fetchedAt": "2026-06-05T21:43:42.779Z",
      "issues": []
    },
    {
      "ticker": "488770",
      "companyName": "KODEX 머니마켓액티브",
      "market": "KR",
      "currency": "KRW",
      "snapshot": {
        "priceDate": "2026-06-06",
        "currentPrice": 104555,
        "previousClose": 104530,
        "previousCloseChangeAmount": 25,
        "previousCloseChangePct": 0.02,
        "priceSession": "previous_close",
        "week52High": 104555,
        "week52Low": 102925,
        "currency": "KRW",
        "sourceNote": "가격 출처: Naver Finance 국내 시세"
      },
      "source": "naver",
      "health": "fresh",
      "staleDays": 0,
      "tradable": true,
      "mode": "normal",
      "fetchedAt": "2026-06-05T21:43:49.709Z",
      "issues": []
    },
    {
      "ticker": "ADBE",
      "companyName": "Adobe",
      "market": "US",
      "currency": "USD",
      "snapshot": {
        "priceDate": "2026-06-06",
        "currentPrice": 250.41,
        "previousCloseChangePct": -3.1,
        "week52High": 419.82,
        "week52Low": 224.13,
        "currency": "USD",
        "sourceNote": "가격 출처: 저장 가격 스냅샷"
      },
      "source": "primary-quote",
      "health": "fresh",
      "staleDays": 0,
      "tradable": true,
      "mode": "normal",
      "fetchedAt": "2026-06-05T21:43:50.071Z",
      "issues": [
        "Yahoo fetch failed: 가격 소스 응답 제한"
      ]
    },
    {
      "ticker": "AMD",
      "companyName": "Advanced Micro Devices",
      "market": "US",
      "currency": "USD",
      "snapshot": {
        "priceDate": "2026-06-06",
        "currentPrice": 467.57,
        "previousCloseChangePct": -10.63,
        "week52High": 546.44,
        "week52Low": 115.06,
        "currency": "USD",
        "sourceNote": "가격 출처: 저장 가격 스냅샷"
      },
      "source": "primary-quote",
      "health": "fresh",
      "staleDays": 0,
      "tradable": true,
      "mode": "normal",
      "fetchedAt": "2026-06-05T21:43:44.453Z",
      "issues": [
        "Yahoo fetch failed: 가격 소스 응답 제한"
      ]
    },
    {
      "ticker": "APLD",
      "companyName": "Applied Digital",
      "market": "US",
      "currency": "USD",
      "snapshot": {
        "priceDate": "2026-06-06",
        "currentPrice": 39.42,
        "previousCloseChangePct": -10.71,
        "week52High": 50.72,
        "week52Low": 9.02,
        "currency": "USD",
        "sourceNote": "가격 출처: 저장 가격 스냅샷"
      },
      "source": "primary-quote",
      "health": "fresh",
      "staleDays": 0,
      "tradable": true,
      "mode": "normal",
      "fetchedAt": "2026-06-05T21:43:46.567Z",
      "issues": [
        "Yahoo fetch failed: 가격 소스 응답 제한"
      ]
    },
    {
      "ticker": "AVGO",
      "companyName": "Broadcom",
      "market": "US",
      "currency": "USD",
      "snapshot": {
        "priceDate": "2026-06-06",
        "currentPrice": 386.9,
        "previousCloseChangePct": -7.64,
        "week52High": 495,
        "week52Low": 241.11,
        "currency": "USD",
        "sourceNote": "가격 출처: 저장 가격 스냅샷"
      },
      "source": "primary-quote",
      "health": "fresh",
      "staleDays": 0,
      "tradable": true,
      "mode": "normal",
      "fetchedAt": "2026-06-05T21:43:44.111Z",
      "issues": [
        "Yahoo fetch failed: 가격 소스 응답 제한"
      ]
    },
    {
      "ticker": "CEG",
      "companyName": "Constellation Energy",
      "market": "US",
      "currency": "USD",
      "snapshot": {
        "priceDate": "2026-06-06",
        "currentPrice": 254.5,
        "previousCloseChangePct": -3.81,
        "week52High": 412.7,
        "week52Low": 243.3,
        "currency": "USD",
        "sourceNote": "가격 출처: 저장 가격 스냅샷"
      },
      "source": "primary-quote",
      "health": "fresh",
      "staleDays": 0,
      "tradable": true,
      "mode": "normal",
      "fetchedAt": "2026-06-05T21:43:42.349Z",
      "issues": [
        "Yahoo fetch failed: 가격 소스 응답 제한"
      ]
    },
    {
      "ticker": "CRM",
      "companyName": "Salesforce",
      "market": "US",
      "currency": "USD",
      "snapshot": {
        "priceDate": "2026-06-06",
        "currentPrice": 185,
        "previousCloseChangePct": -1.99,
        "week52High": 276.8,
        "week52Low": 163.52,
        "currency": "USD",
        "sourceNote": "가격 출처: 저장 가격 스냅샷"
      },
      "source": "primary-quote",
      "health": "fresh",
      "staleDays": 0,
      "tradable": true,
      "mode": "normal",
      "fetchedAt": "2026-06-05T21:43:50.423Z",
      "issues": [
        "Yahoo fetch failed: 가격 소스 응답 제한"
      ]
    },
    {
      "ticker": "DAL",
      "companyName": "Delta Air Lines",
      "market": "US",
      "currency": "USD",
      "snapshot": {
        "priceDate": "2026-06-06",
        "currentPrice": 79.13,
        "previousCloseChangePct": -0.48,
        "week52High": 83.83,
        "week52Low": 45.28,
        "currency": "USD",
        "sourceNote": "가격 출처: 저장 가격 스냅샷"
      },
      "source": "primary-quote",
      "health": "fresh",
      "staleDays": 0,
      "tradable": true,
      "mode": "normal",
      "fetchedAt": "2026-06-05T21:43:50.728Z",
      "issues": [
        "Yahoo fetch failed: 가격 소스 응답 제한"
      ]
    },
    {
      "ticker": "ETN",
      "companyName": "Eaton",
      "market": "US",
      "currency": "USD",
      "snapshot": {
        "priceDate": "2026-06-06",
        "currentPrice": 394.52,
        "previousCloseChangePct": -5.75,
        "week52High": 435.43,
        "week52Low": 311.92,
        "currency": "USD",
        "sourceNote": "가격 출처: 저장 가격 스냅샷"
      },
      "source": "primary-quote",
      "health": "fresh",
      "staleDays": 0,
      "tradable": true,
      "mode": "normal",
      "fetchedAt": "2026-06-05T21:43:41.997Z",
      "issues": [
        "Yahoo fetch failed: 가격 소스 응답 제한"
      ]
    },
    {
      "ticker": "EXPE",
      "companyName": "Expedia",
      "market": "US",
      "currency": "USD",
      "snapshot": {
        "priceDate": "2026-06-06",
        "currentPrice": 228.76,
        "previousCloseChangePct": 0.7,
        "week52High": 303.8,
        "week52Low": 160,
        "currency": "USD",
        "sourceNote": "가격 출처: 저장 가격 스냅샷"
      },
      "source": "primary-quote",
      "health": "fresh",
      "staleDays": 0,
      "tradable": true,
      "mode": "normal",
      "fetchedAt": "2026-06-05T21:43:51.074Z",
      "issues": [
        "Yahoo fetch failed: 가격 소스 응답 제한"
      ]
    },
    {
      "ticker": "FDS",
      "companyName": "FactSet Research Systems",
      "market": "US",
      "currency": "USD",
      "snapshot": {
        "priceDate": "2026-06-06",
        "currentPrice": 255.51,
        "previousCloseChangePct": 0.19,
        "week52High": 453.41,
        "week52Low": 185,
        "currency": "USD",
        "sourceNote": "가격 출처: 저장 가격 스냅샷"
      },
      "source": "primary-quote",
      "health": "fresh",
      "staleDays": 0,
      "tradable": true,
      "mode": "normal",
      "fetchedAt": "2026-06-05T21:43:51.425Z",
      "issues": [
        "Yahoo fetch failed: 가격 소스 응답 제한"
      ]
    },
    {
      "ticker": "NVDA",
      "companyName": "NVIDIA",
      "market": "US",
      "currency": "USD",
      "snapshot": {
        "priceDate": "2026-06-06",
        "currentPrice": 205.4,
        "previousCloseChangePct": -6.06,
        "week52High": 236.54,
        "week52Low": 140.85,
        "currency": "USD",
        "sourceNote": "가격 출처: 저장 가격 스냅샷"
      },
      "source": "primary-quote",
      "health": "fresh",
      "staleDays": 0,
      "tradable": true,
      "mode": "normal",
      "fetchedAt": "2026-06-05T21:43:44.771Z",
      "issues": [
        "Yahoo fetch failed: 가격 소스 응답 제한"
      ]
    },
    {
      "ticker": "OKLO",
      "companyName": "Oklo",
      "market": "US",
      "currency": "USD",
      "snapshot": {
        "priceDate": "2026-06-06",
        "currentPrice": 57.75,
        "previousCloseChangePct": -11.68,
        "week52High": 193.84,
        "week52Low": 44.88,
        "currency": "USD",
        "sourceNote": "가격 출처: 저장 가격 스냅샷"
      },
      "source": "primary-quote",
      "health": "fresh",
      "staleDays": 0,
      "tradable": true,
      "mode": "normal",
      "fetchedAt": "2026-06-05T21:43:46.126Z",
      "issues": [
        "Yahoo fetch failed: 가격 소스 응답 제한"
      ]
    },
    {
      "ticker": "UAL",
      "companyName": "United Airlines",
      "market": "US",
      "currency": "USD",
      "snapshot": {
        "priceDate": "2026-06-06",
        "currentPrice": 105.62,
        "previousCloseChangePct": 0.65,
        "week52High": 119.21,
        "week52Low": 71.55,
        "currency": "USD",
        "sourceNote": "가격 출처: 저장 가격 스냅샷"
      },
      "source": "primary-quote",
      "health": "fresh",
      "staleDays": 0,
      "tradable": true,
      "mode": "normal",
      "fetchedAt": "2026-06-05T21:43:51.776Z",
      "issues": [
        "Yahoo fetch failed: 가격 소스 응답 제한"
      ]
    },
    {
      "ticker": "VST",
      "companyName": "Vistra",
      "market": "US",
      "currency": "USD",
      "snapshot": {
        "priceDate": "2026-06-06",
        "currentPrice": 147.8,
        "previousCloseChangePct": -3.84,
        "week52High": 219.82,
        "week52Low": 132.66,
        "currency": "USD",
        "sourceNote": "가격 출처: 저장 가격 스냅샷"
      },
      "source": "primary-quote",
      "health": "fresh",
      "staleDays": 0,
      "tradable": true,
      "mode": "normal",
      "fetchedAt": "2026-06-05T21:43:46.871Z",
      "issues": [
        "Yahoo fetch failed: 가격 소스 응답 제한"
      ]
    }
  ]
}
